[
    {
        "x": -997,
        "y": 10,
        "z": 55,
        "t": 5,
        "p": "4",
        "rX": 0,
        "rY": 5.846852994181004,
        "rZ": 0
    },
    {
        "x": -1007,
        "y": 11,
        "z": 49,
        "t": 5,
        "p": "4",
        "rX": 0,
        "rY": 6.19591884457987,
        "rZ": 0
    },
    {
        "x": -1024,
        "y": 11,
        "z": 49,
        "t": 5,
        "p": "4",
        "rX": 0,
        "rY": 6.021385919380437,
        "rZ": 0
    },
    {
        "x": -1029,
        "y": 11,
        "z": 41,
        "t": 5,
        "p": "4",
        "rX": 0,
        "rY": 0,
        "rZ": 0
    },
    {
        "x": -1000,
        "y": 10,
        "z": 44,
        "t": 5,
        "p": "4",
        "rX": 0,
        "rY": 0.3490658503988659,
        "rZ": 0
    },
    {
        "x": -997,
        "y": 10,
        "z": 36,
        "t": 5,
        "p": "4",
        "rX": 0,
        "rY": 0.8726646259971648,
        "rZ": 0
    },
    {
        "x": -991,
        "y": 10,
        "z": 43,
        "t": 5,
        "p": "4",
        "rX": 0,
        "rY": 0,
        "rZ": 0
    },
    {
        "x": -984,
        "y": 10,
        "z": 42,
        "t": 5,
        "p": "4",
        "rX": 0,
        "rY": 0.4363323129985824,
        "rZ": 0
    },
    {
        "x": -976,
        "y": 9,
        "z": 46,
        "t": 5,
        "p": "4",
        "rX": 0,
        "rY": 1.0471975511965976,
        "rZ": 0
    },
    {
        "x": -978,
        "y": 9,
        "z": 38,
        "t": 5,
        "p": "4",
        "rX": 0,
        "rY": 0.4363323129985824,
        "rZ": 0
    },
    {
        "x": -989,
        "y": 9,
        "z": 34,
        "t": 5,
        "p": "4",
        "rX": 0,
        "rY": 1.5707963267948966,
        "rZ": 0
    },
    {
        "x": -980,
        "y": 8,
        "z": 30,
        "t": 5,
        "p": "4",
        "rX": 0,
        "rY": 2.007128639793479,
        "rZ": 0
    },
    {
        "x": -974,
        "y": 6,
        "z": 17,
        "t": 5,
        "p": "4",
        "rX": 0,
        "rY": 3.839724354387525,
        "rZ": 0
    },
    {
        "x": -964,
        "y": 6,
        "z": 16,
        "t": 5,
        "p": "4",
        "rX": 0,
        "rY": 4.4505895925855405,
        "rZ": 0
    },
    {
        "x": -963,
        "y": 6,
        "z": 25,
        "t": 5,
        "p": "4",
        "rX": 0,
        "rY": 3.7524578917878086,
        "rZ": 0
    },
    {
        "x": -964,
        "y": 7,
        "z": 33,
        "t": 5,
        "p": "4",
        "rX": 0,
        "rY": 3.141592653589793,
        "rZ": 0
    },
    {
        "x": -956,
        "y": 6,
        "z": 30,
        "t": 5,
        "p": "4",
        "rX": 0,
        "rY": 3.5779249665883754,
        "rZ": 0
    },
    {
        "x": -998,
        "y": 8,
        "z": 15,
        "t": 5,
        "p": "4",
        "rX": 0,
        "rY": 4.71238898038469,
        "rZ": 0
    },
    {
        "x": -1007,
        "y": 8,
        "z": 12,
        "t": 5,
        "p": "4",
        "rX": 0,
        "rY": 5.061454830783556,
        "rZ": 0
    },
    {
        "x": -1013,
        "y": 8,
        "z": 10,
        "t": 5,
        "p": "4",
        "rX": 0,
        "rY": 5.672320068981571,
        "rZ": 0
    },
    {
        "x": -1003,
        "y": 9,
        "z": 25,
        "t": 5,
        "p": "4",
        "rX": 0,
        "rY": 5.585053606381854,
        "rZ": 0
    },
    {
        "x": -1033,
        "y": 10,
        "z": 34,
        "t": 5,
        "p": "4",
        "rX": 0,
        "rY": 0.5235987755982988,
        "rZ": 0
    },
    {
        "x": -1036,
        "y": 10,
        "z": 27,
        "t": 5,
        "p": "4",
        "rX": 0,
        "rY": 5.846852994181004,
        "rZ": 0
    },
    {
        "x": -1044,
        "y": 10,
        "z": 24,
        "t": 5,
        "p": "4",
        "rX": 0,
        "rY": 0.8726646259971648,
        "rZ": 0
    },
    {
        "x": -1041,
        "y": 9,
        "z": 17,
        "t": 5,
        "p": "4",
        "rX": 0,
        "rY": 0.08726646259971647,
        "rZ": 0
    },
    {
        "x": -1034,
        "y": 9,
        "z": 18,
        "t": 5,
        "p": "4",
        "rX": 0,
        "rY": 1.1344640137963142,
        "rZ": 0
    },
    {
        "x": -1022,
        "y": 8,
        "z": 8,
        "t": 5,
        "p": "4",
        "rX": 0,
        "rY": 1.4835298641951802,
        "rZ": 0
    },
    {
        "x": -1028,
        "y": 8,
        "z": 2,
        "t": 5,
        "p": "4",
        "rX": 0,
        "rY": 0.9599310885968813,
        "rZ": 0
    },
    {
        "x": -1019,
        "y": 7,
        "z": -2,
        "t": 5,
        "p": "4",
        "rX": 0,
        "rY": 1.4835298641951802,
        "rZ": 0
    },
    {
        "x": -1012,
        "y": 7,
        "z": 1,
        "t": 5,
        "p": "4",
        "rX": 0,
        "rY": 1.9198621771937625,
        "rZ": 0
    },
    {
        "x": -1026,
        "y": 7,
        "z": -4,
        "t": 5,
        "p": "4",
        "rX": 0,
        "rY": 2.0943951023931953,
        "rZ": 0
    },
    {
        "x": -1026,
        "y": 6,
        "z": -11,
        "t": 5,
        "p": "4",
        "rX": 0,
        "rY": 2.443460952792061,
        "rZ": 0
    },
    {
        "x": -1033,
        "y": 6,
        "z": -15,
        "t": 5,
        "p": "4",
        "rX": 0,
        "rY": 2.8797932657906435,
        "rZ": 0
    },
    {
        "x": -1041,
        "y": 6,
        "z": -15,
        "t": 5,
        "p": "4",
        "rX": 0,
        "rY": 2.443460952792061,
        "rZ": 0
    },
    {
        "x": -1034,
        "y": 7,
        "z": -7,
        "t": 5,
        "p": "4",
        "rX": 0,
        "rY": 2.0943951023931953,
        "rZ": 0
    },
    {
        "x": -1048,
        "y": 7,
        "z": -13,
        "t": 5,
        "p": "4",
        "rX": 0,
        "rY": 2.356194490192345,
        "rZ": 0
    },
    {
        "x": -1051,
        "y": 8,
        "z": -5,
        "t": 5,
        "p": "4",
        "rX": 0,
        "rY": 1.8325957145940461,
        "rZ": 0
    },
    {
        "x": -1053,
        "y": 8,
        "z": 1,
        "t": 5,
        "p": "4",
        "rX": 0,
        "rY": 2.2689280275926285,
        "rZ": 0
    },
    {
        "x": -1049,
        "y": 9,
        "z": 8,
        "t": 5,
        "p": "4",
        "rX": 0,
        "rY": 1.8325957145940461,
        "rZ": 0
    },
    {
        "x": -1053,
        "y": 10,
        "z": 14,
        "t": 5,
        "p": "4",
        "rX": 0,
        "rY": 2.2689280275926285,
        "rZ": 0
    },
    {
        "x": -1041,
        "y": 8,
        "z": 0,
        "t": 5,
        "p": "4",
        "rX": 0,
        "rY": 1.9198621771937625,
        "rZ": 0
    },
    {
        "x": -1040,
        "y": 8,
        "z": 9,
        "t": 5,
        "p": "4",
        "rX": 0,
        "rY": 2.181661564992912,
        "rZ": 0
    },
    {
        "x": -1029,
        "y": 9,
        "z": 13,
        "t": 5,
        "p": "4",
        "rX": 0,
        "rY": 1.8325957145940461,
        "rZ": 0
    },
    {
        "x": -1063,
        "y": 10,
        "z": 9,
        "t": 5,
        "p": "4",
        "rX": 0,
        "rY": 1.8325957145940461,
        "rZ": 0
    },
    {
        "x": -1060,
        "y": 8,
        "z": -8,
        "t": 5,
        "p": "4",
        "rX": 0,
        "rY": 1.4835298641951802,
        "rZ": 0
    },
    {
        "x": -1056,
        "y": 7,
        "z": -18,
        "t": 5,
        "p": "4",
        "rX": 0,
        "rY": 1.9198621771937625,
        "rZ": 0
    },
    {
        "x": -1047,
        "y": 6,
        "z": -21,
        "t": 5,
        "p": "4",
        "rX": 0,
        "rY": 1.3962634015954636,
        "rZ": 0
    },
    {
        "x": -1030,
        "y": 5,
        "z": -21,
        "t": 5,
        "p": "4",
        "rX": 0,
        "rY": 1.4835298641951802,
        "rZ": 0
    },
    {
        "x": -1021,
        "y": 5,
        "z": -22,
        "t": 5,
        "p": "4",
        "rX": 0,
        "rY": 1.1344640137963142,
        "rZ": 0
    },
    {
        "x": -1037,
        "y": 4,
        "z": -31,
        "t": 5,
        "p": "4",
        "rX": 0,
        "rY": 1.4835298641951802,
        "rZ": 0
    },
    {
        "x": -953,
        "y": 7,
        "z": 43,
        "t": 5,
        "p": "4",
        "rX": 0,
        "rY": 6.19591884457987,
        "rZ": 0
    },
    {
        "x": -958,
        "y": 8,
        "z": 49,
        "t": 5,
        "p": "4",
        "rX": 0,
        "rY": 0.2617993877991494,
        "rZ": 0
    },
    {
        "x": -965,
        "y": 8,
        "z": 45,
        "t": 5,
        "p": "4",
        "rX": 0,
        "rY": 5.497787143782138,
        "rZ": 0
    },
    {
        "x": -952.12,
        "y": 4.61,
        "z": 21.57,
        "t": 5,
        "p": "5",
        "rX": 0,
        "rY": 6.021385919380437,
        "rZ": 0
    },
    {
        "x": -987.42,
        "y": 9.44,
        "z": 49.8,
        "t": 5,
        "p": "5",
        "rX": 0,
        "rY": 5.672320068981571,
        "rZ": 0
    },
    {
        "x": -987.32,
        "y": 7.82,
        "z": 28.96,
        "t": 5,
        "p": "5",
        "rX": 0,
        "rY": 5.323254218582705,
        "rZ": 0
    },
    {
        "x": -1015.09,
        "y": 10.21,
        "z": 53.58,
        "t": 5,
        "p": "5",
        "rX": 0,
        "rY": 4.799655442984406,
        "rZ": 0
    },
    {
        "x": -996.96,
        "y": 5.34,
        "z": 0.21,
        "t": 5,
        "p": "5",
        "rX": 0,
        "rY": 3.9269908169872414,
        "rZ": 0
    },
    {
        "x": -1021.65,
        "y": 4.75,
        "z": -15.18,
        "t": 5,
        "p": "5",
        "rX": 0,
        "rY": 2.530727415391778,
        "rZ": 0
    },
    {
        "x": -1055.25,
        "y": 6.62,
        "z": -11.05,
        "t": 5,
        "p": "5",
        "rX": 0,
        "rY": 1.2217304763960306,
        "rZ": 0
    },
    {
        "x": -1047.28,
        "y": 8.66,
        "z": 15.72,
        "t": 5,
        "p": "5",
        "rX": 0,
        "rY": 0.8726646259971648,
        "rZ": 0
    },
    {
        "x": -1020,
        "y": 9.23,
        "z": 28,
        "t": 5,
        "p": 112,
        "rX": 0,
        "rY": 0,
        "rZ": 0
    }
]