[
    {
        "x": -203.42,
        "y": 3.27,
        "z": 221.95,
        "t": 5,
        "p": "30",
        "rX": 0,
        "rY": 4.4505895925855405,
        "rZ": 0
    },
    {
        "x": -196.46,
        "y": 5.12,
        "z": 197.86,
        "t": 5,
        "p": "30",
        "rX": 0,
        "rY": 3.4033920413889427,
        "rZ": 0
    },
    {
        "x": -192.46,
        "y": 4.85,
        "z": 204.63,
        "t": 5,
        "p": "29",
        "rX": 0,
        "rY": 5.846852994181004,
        "rZ": 0
    },
    {
        "x": -180.57,
        "y": 5.97,
        "z": 200.47,
        "t": 5,
        "p": "29",
        "rX": 0,
        "rY": 5.846852994181004,
        "rZ": 0
    },
    {
        "x": -181.15,
        "y": 5.7,
        "z": 201.44,
        "t": 5,
        "p": "29",
        "rX": 0,
        "rY": 5.497787143782138,
        "rZ": 0
    },
    {
        "x": -181.44,
        "y": 6.13,
        "z": 200.57,
        "t": 5,
        "p": "29",
        "rX": 0,
        "rY": 5.061454830783556,
        "rZ": 0
    },
    {
        "x": -193.41,
        "y": 3.91,
        "z": 204.47,
        "t": 5,
        "p": "29",
        "rX": 0,
        "rY": 5.061454830783556,
        "rZ": 0
    },
    {
        "x": -191.37,
        "y": 3.84,
        "z": 204.23,
        "t": 5,
        "p": "29",
        "rX": 0,
        "rY": 5.061454830783556,
        "rZ": 0
    }
]