[
    {
        "x": 151,
        "y": 49.71,
        "z": 241,
        "t": 5,
        "p": 22,
        "rX": 0,
        "rY": 0.822569785157032,
        "rZ": 0
    },
    {
        "x": 159,
        "y": 50.25,
        "z": 236,
        "t": 5,
        "p": 22,
        "rX": 0,
        "rY": 0.5123777220315916,
        "rZ": 0
    },
    {
        "x": 148,
        "y": 49.56,
        "z": 242,
        "t": 5,
        "p": "38",
        "rX": 0,
        "rY": 0,
        "rZ": 0
    },
    {
        "x": 149,
        "y": 49.56,
        "z": 243,
        "t": 5,
        "p": "38",
        "rX": 0,
        "rY": 0,
        "rZ": 0
    },
    {
        "x": 150,
        "y": 49.53,
        "z": 244,
        "t": 5,
        "p": "38",
        "rX": 0,
        "rY": 0,
        "rZ": 0
    },
    {
        "x": 148,
        "y": 49.51,
        "z": 243,
        "t": 5,
        "p": "38",
        "rX": 0,
        "rY": 0,
        "rZ": 0
    },
    {
        "x": 159,
        "y": 50.09,
        "z": 239,
        "t": 5,
        "p": "38",
        "rX": 0,
        "rY": 0,
        "rZ": 0
    },
    {
        "x": 164,
        "y": 50.56,
        "z": 233,
        "t": 5,
        "p": "97",
        "rX": 0,
        "rY": 0,
        "rZ": 0
    },
    {
        "x": 164,
        "y": 51.06,
        "z": 233,
        "t": 5,
        "p": "97",
        "rX": 0,
        "rY": 0,
        "rZ": 0
    },
    {
        "x": 152,
        "y": 49.62,
        "z": 243,
        "t": 5,
        "p": "97",
        "rX": 0,
        "rY": 0,
        "rZ": 0
    },
    {
        "x": 156,
        "y": 50.18,
        "z": 236,
        "t": 5,
        "p": "76",
        "rX": 0,
        "rY": 0,
        "rZ": 0
    },
    {
        "x": 157,
        "y": 50.11,
        "z": 238,
        "t": 5,
        "p": "98",
        "rX": 0,
        "rY": 0,
        "rZ": 0
    },
    {
        "x": 166.39,
        "y": 50.77,
        "z": 231.12,
        "t": 5,
        "p": 22,
        "rX": 0,
        "rY": 0.34404741367226943,
        "rZ": 0
    },
    {
        "x": 157.52,
        "y": 51.08,
        "z": 238.88,
        "t": 5,
        "p": 102,
        "rX": -1.5855977629192273,
        "rY": 0,
        "rZ": 0
    },
    {
        "x": 167,
        "y": 50.65,
        "z": 234,
        "t": 5,
        "p": "87",
        "rX": 0,
        "rY": 0,
        "rZ": 0
    },
    {
        "x": 166,
        "y": 50.62,
        "z": 234,
        "t": 5,
        "p": "87",
        "rX": 0,
        "rY": 0,
        "rZ": 0
    },
    {
        "x": 162,
        "y": 50.32,
        "z": 237,
        "t": 5,
        "p": "87",
        "rX": 0,
        "rY": 0,
        "rZ": 0
    }
]