[
    {
        "x": -108,
        "y": 10.4,
        "z": 47,
        "t": 5,
        "p": "4",
        "rX": 0,
        "rY": 4.537856055185257,
        "rZ": 0
    },
    {
        "x": -117,
        "y": 8.4,
        "z": 49,
        "t": 5,
        "p": "4",
        "rX": 0,
        "rY": 4.537856055185257,
        "rZ": 0
    },
    {
        "x": -135,
        "y": 3.4,
        "z": 51,
        "t": 5,
        "p": "4",
        "rX": 0,
        "rY": 3.9269908169872414,
        "rZ": 0
    },
    {
        "x": -131,
        "y": 3.4,
        "z": 44,
        "t": 5,
        "p": "4",
        "rX": 0,
        "rY": 3.5779249665883754,
        "rZ": 0
    },
    {
        "x": -152.84,
        "y": 1.92,
        "z": 17.25,
        "t": 5,
        "p": "30",
        "rX": 0,
        "rY": 0,
        "rZ": 0
    },
    {
        "x": -167.33,
        "y": 0.54,
        "z": 50.1,
        "t": 5,
        "p": "30",
        "rX": 0,
        "rY": 0.08726646259971647,
        "rZ": 0
    },
    {
        "x": -127.7,
        "y": 4.32,
        "z": -38.43,
        "t": 5,
        "p": 5,
        "rX": 0,
        "rY": -0.3490658503988658,
        "rZ": 0
    },
    {
        "x": -132.26,
        "y": 7.39,
        "z": -18.54,
        "t": 5,
        "p": 5,
        "rX": 0,
        "rY": 0,
        "rZ": 0
    },
    {
        "x": -138.53,
        "y": 6.86,
        "z": -31.68,
        "t": 5,
        "p": 4,
        "rX": 0,
        "rY": -0.4363323129985821,
        "rZ": 0
    },
    {
        "x": -107.68,
        "y": 5.97,
        "z": -26.42,
        "t": 5,
        "p": 4,
        "rX": 0,
        "rY": -1.308996938995748,
        "rZ": 0
    }
]