[
    {
        "x": 176,
        "y": 0.38,
        "z": -122.2,
        "t": 5,
        "p": 54,
        "rX": 0,
        "rY": 0.8635993800426665,
        "rZ": 0
    },
    {
        "x": 178,
        "y": 0.38,
        "z": -61,
        "t": 5,
        "p": "1141",
        "rX": 0,
        "rY": 0,
        "rZ": 0,
        "metadata": {
            "t1": "28"
        }
    },
    {
        "x": 176,
        "y": 0.38,
        "z": -122,
        "t": 5,
        "p": 54,
        "rX": -3.141592653589793,
        "rY": -0.3366799875962582,
        "rZ": -3.141592653589793
    },
    {
        "x": 181,
        "y": 0.38,
        "z": -107,
        "t": 5,
        "p": 54,
        "rX": 3.141592653589793,
        "rY": 0.4199840551926505,
        "rZ": 3.141592653589793
    },
    {
        "x": 175,
        "y": 0.38,
        "z": -121,
        "t": 5,
        "p": "46",
        "rX": 0,
        "rY": 0,
        "rZ": 0
    },
    {
        "x": 180,
        "y": 0.38,
        "z": -107,
        "t": 5,
        "p": "46",
        "rX": 0,
        "rY": 0,
        "rZ": 0
    },
    {
        "x": 168.52,
        "y": 0.37,
        "z": -87.3,
        "t": 5,
        "p": 1,
        "rX": 0,
        "rY": 0.5536087776491314,
        "rZ": 0
    },
    {
        "x": 177,
        "y": 0.38,
        "z": -95,
        "t": 5,
        "p": "46",
        "rX": 0,
        "rY": 0,
        "rZ": 0
    },
    {
        "x": 168,
        "y": 0.37,
        "z": -88,
        "t": 5,
        "p": 49,
        "rX": 0,
        "rY": 0.6425507778020048,
        "rZ": 0
    }
]