[
    {
        "x": 31.25,
        "y": 0,
        "z": -57.87,
        "t": 5,
        "p": "97",
        "rX": 0,
        "rY": 0.4499999999999998,
        "rZ": 0
    },
    {
        "x": 30.14,
        "y": 0,
        "z": -56.45,
        "t": 5,
        "p": "97",
        "rX": 0,
        "rY": 5.6331853071795885,
        "rZ": 0
    },
    {
        "x": 30.77,
        "y": 0,
        "z": -68.36,
        "t": 5,
        "p": "39",
        "rX": 0,
        "rY": 0,
        "rZ": 0,
        "metadata": {
            "t1": "35"
        }
    },
    {
        "x": 30.78,
        "y": 0,
        "z": -62.34,
        "t": 5,
        "p": "66",
        "rX": 0,
        "rY": 0,
        "rZ": 0,
        "metadata": {
            "t1": "35"
        }
    },
    {
        "x": 3,
        "y": 0,
        "z": -63,
        "t": 5,
        "p": "50",
        "rX": 0,
        "rY": 0,
        "rZ": 0
    },
    {
        "x": 3,
        "y": 0,
        "z": -68,
        "t": 5,
        "p": "50",
        "rX": 0,
        "rY": 0,
        "rZ": 0
    },
    {
        "x": 9,
        "y": 0,
        "z": -68,
        "t": 5,
        "p": "50",
        "rX": 0,
        "rY": 0,
        "rZ": 0
    },
    {
        "x": 5.39,
        "y": 0,
        "z": -67.06,
        "t": 5,
        "p": "87",
        "rX": 0,
        "rY": 0,
        "rZ": 0
    },
    {
        "x": 6.32,
        "y": 0,
        "z": -68.27,
        "t": 5,
        "p": "87",
        "rX": 0,
        "rY": 0,
        "rZ": 0
    },
    {
        "x": 7.05,
        "y": 0,
        "z": -66.74,
        "t": 5,
        "p": "87",
        "rX": 0,
        "rY": 0,
        "rZ": 0
    },
    {
        "x": 3.68,
        "y": 0,
        "z": -65.63,
        "t": 5,
        "p": "87",
        "rX": 0,
        "rY": 0,
        "rZ": 0
    },
    {
        "x": 5.11,
        "y": 0,
        "z": -61.85,
        "t": 5,
        "p": "87",
        "rX": 0,
        "rY": 0,
        "rZ": 0
    },
    {
        "x": 2.56,
        "y": 0,
        "z": -60.79,
        "t": 5,
        "p": "87",
        "rX": 0,
        "rY": 0,
        "rZ": 0
    },
    {
        "x": 11.29,
        "y": 0,
        "z": -67.67,
        "t": 5,
        "p": "87",
        "rX": 0,
        "rY": 0,
        "rZ": 0
    },
    {
        "x": 2.58,
        "y": 0,
        "z": -57.91,
        "t": 5,
        "p": "87",
        "rX": 0,
        "rY": 0,
        "rZ": 0
    },
    {
        "x": 1.81,
        "y": 0,
        "z": -58.82,
        "t": 5,
        "p": "91",
        "rX": 0,
        "rY": 0,
        "rZ": 0
    },
    {
        "x": 3.2,
        "y": 0,
        "z": -58.54,
        "t": 5,
        "p": "91",
        "rX": 0,
        "rY": 0,
        "rZ": 0
    },
    {
        "x": 3.69,
        "y": 0,
        "z": -60.82,
        "t": 5,
        "p": "91",
        "rX": 0,
        "rY": 0,
        "rZ": 0
    },
    {
        "x": 4.79,
        "y": 0,
        "z": -65.98,
        "t": 5,
        "p": "91",
        "rX": 0,
        "rY": 0,
        "rZ": 0
    },
    {
        "x": 5.44,
        "y": 0,
        "z": -68.3,
        "t": 5,
        "p": "91",
        "rX": 0,
        "rY": 0,
        "rZ": 0
    },
    {
        "x": 6.19,
        "y": 0,
        "z": -66.81,
        "t": 5,
        "p": "91",
        "rX": 0,
        "rY": 0,
        "rZ": 0
    },
    {
        "x": 11.21,
        "y": 0,
        "z": -66.87,
        "t": 5,
        "p": "91",
        "rX": 0,
        "rY": 0,
        "rZ": 0
    },
    {
        "x": 12.41,
        "y": 0,
        "z": -67.99,
        "t": 5,
        "p": "91",
        "rX": 0,
        "rY": 0,
        "rZ": 0
    },
    {
        "x": 14.49,
        "y": 0,
        "z": -68.62,
        "t": 5,
        "p": "96",
        "rX": 0,
        "rY": 4.433185307179591,
        "rZ": 0
    },
    {
        "x": 19.89,
        "y": 0,
        "z": -59.91,
        "t": 5,
        "p": "35",
        "rX": 0,
        "rY": 5.733185307179588,
        "rZ": 0,
        "metadata": {
            "t1": "25"
        }
    },
    {
        "x": 17.34,
        "y": 0,
        "z": -58.37,
        "t": 5,
        "p": "35",
        "rX": 0,
        "rY": 0.4999999999999998,
        "rZ": 0,
        "metadata": {
            "t1": "25"
        }
    },
    {
        "x": 20.24,
        "y": 0,
        "z": -57.41,
        "t": 5,
        "p": "35",
        "rX": 0,
        "rY": 0.19999999999999984,
        "rZ": 0,
        "metadata": {
            "t1": "25"
        }
    },
    {
        "x": 17.96,
        "y": 0,
        "z": -61.88,
        "t": 5,
        "p": "35",
        "rX": 0,
        "rY": 0.8000000000000002,
        "rZ": 0,
        "metadata": {
            "t1": "25"
        }
    },
    {
        "x": 27.73,
        "y": 0,
        "z": -67.62,
        "t": 5,
        "p": "35",
        "rX": 0,
        "rY": 0,
        "rZ": 0
    },
    {
        "x": 25.11,
        "y": 0,
        "z": -68.9,
        "t": 5,
        "p": "35",
        "rX": 0,
        "rY": 0,
        "rZ": 0
    },
    {
        "x": 22.44,
        "y": 0,
        "z": -69.9,
        "t": 5,
        "p": "99",
        "rX": 0,
        "rY": 0,
        "rZ": 0
    },
    {
        "x": 21.05,
        "y": 0,
        "z": -69.94,
        "t": 5,
        "p": "99",
        "rX": 0,
        "rY": 0,
        "rZ": 0
    },
    {
        "x": 19.63,
        "y": 0,
        "z": -69.98,
        "t": 5,
        "p": "99",
        "rX": 0,
        "rY": 0,
        "rZ": 0
    },
    {
        "x": 19.54,
        "y": 0,
        "z": -66.63,
        "t": 5,
        "p": "36",
        "rX": 0,
        "rY": 5.6331853071795885,
        "rZ": 0
    },
    {
        "x": 25,
        "y": 0.86,
        "z": -67,
        "t": 5,
        "p": "36",
        "rX": 3.1331853071795925,
        "rY": 1.7763568394002505e-15,
        "rZ": 0
    },
    {
        "x": 19.91,
        "y": 0,
        "z": -67.84,
        "t": 5,
        "p": "34",
        "rX": 0,
        "rY": 4.033185307179592,
        "rZ": 0
    },
    {
        "x": 20.71,
        "y": 0,
        "z": -65.75,
        "t": 5,
        "p": "34",
        "rX": 0,
        "rY": 2.4831853071795944,
        "rZ": 0
    },
    {
        "x": 35.72,
        "y": 0,
        "z": -60.94,
        "t": 5,
        "p": "55",
        "rX": 0,
        "rY": 0,
        "rZ": 0,
        "metadata": {
            "t1": "35"
        }
    },
    {
        "x": 47.73,
        "y": 0,
        "z": -69.06,
        "t": 5,
        "p": "96",
        "rX": 0,
        "rY": 0,
        "rZ": 0
    },
    {
        "x": 47.63,
        "y": 0,
        "z": -67.49,
        "t": 5,
        "p": "97",
        "rX": 0,
        "rY": 0,
        "rZ": 0
    },
    {
        "x": 49.3,
        "y": 0,
        "z": -69.07,
        "t": 5,
        "p": "97",
        "rX": 0,
        "rY": 0.9500000000000012,
        "rZ": 0
    },
    {
        "x": 44.76,
        "y": 0,
        "z": -65.02,
        "t": 5,
        "p": "38",
        "rX": 0,
        "rY": 0,
        "rZ": 0
    },
    {
        "x": 45.87,
        "y": 0,
        "z": -65.09,
        "t": 5,
        "p": "38",
        "rX": 0,
        "rY": 0,
        "rZ": 0
    },
    {
        "x": 49.09,
        "y": 0,
        "z": -56.77,
        "t": 5,
        "p": "37",
        "rX": 0,
        "rY": 0,
        "rZ": 0
    },
    {
        "x": 47.65,
        "y": 0,
        "z": -56.99,
        "t": 5,
        "p": "37",
        "rX": 0,
        "rY": 5.383185307179589,
        "rZ": 0
    },
    {
        "x": 47.56,
        "y": 0,
        "z": -58.92,
        "t": 5,
        "p": "38",
        "rX": 0,
        "rY": 0,
        "rZ": 0
    },
    {
        "x": 47.56,
        "y": 0,
        "z": -60.18,
        "t": 5,
        "p": "38",
        "rX": 0,
        "rY": 0,
        "rZ": 0
    },
    {
        "x": 46.88,
        "y": 3.8,
        "z": -58.44,
        "t": 5,
        "p": "104",
        "rX": 0,
        "rY": 1.6831853071795952,
        "rZ": 0
    },
    {
        "x": 46.88,
        "y": 4,
        "z": -68.06,
        "t": 5,
        "p": "104",
        "rX": 0,
        "rY": 1.6831853071795952,
        "rZ": 0
    },
    {
        "x": 36.22,
        "y": 3.75,
        "z": -63.19,
        "t": 5,
        "p": "104",
        "rX": 0,
        "rY": 1.6831853071795952,
        "rZ": 0
    },
    {
        "x": 55.83,
        "y": 0,
        "z": -60.53,
        "t": 5,
        "p": "38",
        "rX": 0,
        "rY": 0,
        "rZ": 0
    },
    {
        "x": 55.81,
        "y": 1.51,
        "z": -60.39,
        "t": 5,
        "p": "91",
        "rX": 0,
        "rY": 0,
        "rZ": 0
    },
    {
        "x": 47.4,
        "y": 4.19,
        "z": -58.56,
        "t": 5,
        "p": "108",
        "rX": 0,
        "rY": 0,
        "rZ": 0
    },
    {
        "x": 36.74,
        "y": 4.16,
        "z": -63.17,
        "t": 5,
        "p": "108",
        "rX": 0,
        "rY": 0,
        "rZ": 0
    },
    {
        "x": 47.27,
        "y": 4.29,
        "z": -67.93,
        "t": 5,
        "p": "108",
        "rX": 0,
        "rY": 0,
        "rZ": 0
    },
    {
        "x": 52.66,
        "y": 0,
        "z": -77.85,
        "t": 5,
        "p": "35",
        "rX": 0,
        "rY": 0,
        "rZ": 0
    },
    {
        "x": 54.81,
        "y": 0,
        "z": -79.99,
        "t": 5,
        "p": "35",
        "rX": 0,
        "rY": 0.65,
        "rZ": 0
    },
    {
        "x": 55.27,
        "y": 0,
        "z": -82.39,
        "t": 5,
        "p": "35",
        "rX": 0,
        "rY": 6.283185307179586,
        "rZ": 0
    },
    {
        "x": 54.96,
        "y": 2.01,
        "z": -81.15,
        "t": 5,
        "p": "35",
        "rX": 0,
        "rY": 6.283185307179586,
        "rZ": 0
    },
    {
        "x": 53.26,
        "y": 0,
        "z": -81.89,
        "t": 5,
        "p": "35",
        "rX": 0,
        "rY": 6.283185307179586,
        "rZ": 0
    },
    {
        "x": 55.46,
        "y": 0,
        "z": -88.14,
        "t": 5,
        "p": "96",
        "rX": 0,
        "rY": 0,
        "rZ": 0
    },
    {
        "x": 53.96,
        "y": 0,
        "z": -88.13,
        "t": 5,
        "p": "96",
        "rX": 0,
        "rY": 0,
        "rZ": 0
    },
    {
        "x": 53.92,
        "y": 0.11,
        "z": -88.23,
        "t": 5,
        "p": "97",
        "rX": 0,
        "rY": 4.733185307179592,
        "rZ": 0
    },
    {
        "x": 55.48,
        "y": 0.11,
        "z": -88.25,
        "t": 5,
        "p": "97",
        "rX": 0,
        "rY": 4.733185307179592,
        "rZ": 0
    },
    {
        "x": 53.96,
        "y": 0.65,
        "z": -88.3,
        "t": 5,
        "p": "97",
        "rX": 0,
        "rY": 4.733185307179592,
        "rZ": 0
    },
    {
        "x": 55.45,
        "y": 0.63,
        "z": -88.31,
        "t": 5,
        "p": "97",
        "rX": 0,
        "rY": 4.733185307179592,
        "rZ": 0
    },
    {
        "x": 41.89,
        "y": 0,
        "z": -90.03,
        "t": 5,
        "p": "51",
        "rX": 0,
        "rY": 0,
        "rZ": 0
    },
    {
        "x": 27.35,
        "y": 0,
        "z": -93.86,
        "t": 5,
        "p": "51",
        "rX": 0,
        "rY": 0,
        "rZ": 0
    },
    {
        "x": 36.07,
        "y": 0,
        "z": -107.05,
        "t": 5,
        "p": "51",
        "rX": 0,
        "rY": 0,
        "rZ": 0
    },
    {
        "x": 49.25,
        "y": 0,
        "z": -84.88,
        "t": 5,
        "p": "13",
        "rX": 0,
        "rY": 0,
        "rZ": 0
    },
    {
        "x": 47.25,
        "y": 0,
        "z": -84.83,
        "t": 5,
        "p": "98",
        "rX": 0,
        "rY": 0,
        "rZ": 0
    },
    {
        "x": 39.69,
        "y": 0,
        "z": -92.73,
        "t": 5,
        "p": "35",
        "rX": 0,
        "rY": 5.733185307179587,
        "rZ": 0
    },
    {
        "x": 40.69,
        "y": 0,
        "z": -95.6,
        "t": 5,
        "p": "35",
        "rX": 0,
        "rY": 6.283185307179585,
        "rZ": 0
    },
    {
        "x": 29.59,
        "y": 0,
        "z": -80.8,
        "t": 5,
        "p": "35",
        "rX": 0,
        "rY": 6.283185307179585,
        "rZ": 0
    },
    {
        "x": 29.38,
        "y": 0,
        "z": -82.9,
        "t": 5,
        "p": "35",
        "rX": 0,
        "rY": 6.283185307179585,
        "rZ": 0
    },
    {
        "x": 31.68,
        "y": 0,
        "z": -80.77,
        "t": 5,
        "p": "35",
        "rX": 0,
        "rY": 6.283185307179585,
        "rZ": 0
    },
    {
        "x": 31.69,
        "y": 0,
        "z": -82.82,
        "t": 5,
        "p": "35",
        "rX": 0,
        "rY": 6.283185307179585,
        "rZ": 0
    },
    {
        "x": 29.33,
        "y": 0,
        "z": -84.98,
        "t": 5,
        "p": "35",
        "rX": 0,
        "rY": 6.283185307179585,
        "rZ": 0
    },
    {
        "x": 33.7,
        "y": 0,
        "z": -80.71,
        "t": 5,
        "p": "35",
        "rX": 0,
        "rY": 6.283185307179585,
        "rZ": 0
    },
    {
        "x": 33.82,
        "y": 0,
        "z": -82.72,
        "t": 5,
        "p": "35",
        "rX": 0,
        "rY": 6.283185307179585,
        "rZ": 0
    },
    {
        "x": 31.58,
        "y": 0,
        "z": -84.89,
        "t": 5,
        "p": "35",
        "rX": 0,
        "rY": 6.283185307179585,
        "rZ": 0
    },
    {
        "x": 29.66,
        "y": 2.01,
        "z": -83.76,
        "t": 5,
        "p": "35",
        "rX": 0,
        "rY": 0,
        "rZ": 0
    },
    {
        "x": 29.44,
        "y": 2.01,
        "z": -81.37,
        "t": 5,
        "p": "35",
        "rX": 0,
        "rY": 0,
        "rZ": 0
    },
    {
        "x": 31.92,
        "y": 2.01,
        "z": -81.02,
        "t": 5,
        "p": "35",
        "rX": 0,
        "rY": 0,
        "rZ": 0
    },
    {
        "x": 32.16,
        "y": 2.01,
        "z": -83.54,
        "t": 5,
        "p": "35",
        "rX": 0,
        "rY": 5.583185307179589,
        "rZ": 0
    },
    {
        "x": 30.44,
        "y": 3.9,
        "z": -81.7,
        "t": 5,
        "p": "35",
        "rX": 0,
        "rY": 5.0831853071795905,
        "rZ": 0
    },
    {
        "x": 35.6,
        "y": 0,
        "z": -80.31,
        "t": 5,
        "p": "97",
        "rX": 0,
        "rY": 0,
        "rZ": 0
    },
    {
        "x": 35.64,
        "y": 0,
        "z": -81.59,
        "t": 5,
        "p": "97",
        "rX": 0,
        "rY": 0,
        "rZ": 0
    },
    {
        "x": 35.64,
        "y": 0.46,
        "z": -80.86,
        "t": 5,
        "p": "97",
        "rX": 0,
        "rY": 0,
        "rZ": 0
    },
    {
        "x": 29.29,
        "y": 0,
        "z": -86.83,
        "t": 5,
        "p": "96",
        "rX": 0,
        "rY": 0,
        "rZ": 0
    },
    {
        "x": 29.25,
        "y": 0,
        "z": -88.85,
        "t": 5,
        "p": "96",
        "rX": 0,
        "rY": 0,
        "rZ": 0
    },
    {
        "x": 29.23,
        "y": 0.11,
        "z": -87.02,
        "t": 5,
        "p": "97",
        "rX": 0,
        "rY": 4.73318530717959,
        "rZ": 0
    },
    {
        "x": 29.27,
        "y": 0.65,
        "z": -86.99,
        "t": 5,
        "p": "97",
        "rX": 0,
        "rY": 4.73318530717959,
        "rZ": 0
    },
    {
        "x": 29.16,
        "y": 0.11,
        "z": -88.87,
        "t": 5,
        "p": "97",
        "rX": 0,
        "rY": 4.73318530717959,
        "rZ": 0
    },
    {
        "x": 29.24,
        "y": 0.64,
        "z": -88.91,
        "t": 5,
        "p": "97",
        "rX": 0,
        "rY": 4.73318530717959,
        "rZ": 0
    },
    {
        "x": 41.06,
        "y": 0,
        "z": -80.85,
        "t": 5,
        "p": "35",
        "rX": 0,
        "rY": 0,
        "rZ": 0
    },
    {
        "x": 37.54,
        "y": 0,
        "z": -95.1,
        "t": 5,
        "p": "35",
        "rX": 0,
        "rY": 0.6,
        "rZ": 0
    },
    {
        "x": 38.24,
        "y": 0,
        "z": -88.64,
        "t": 5,
        "p": "35",
        "rX": 0,
        "rY": 0.2999999999999998,
        "rZ": 0
    }
]